visualone/__init__.py
visualone/utils.py
visualone/vedx.py
visualone-0.0.20.dist-info/LICENSE
visualone-0.0.20.dist-info/METADATA
visualone-0.0.20.dist-info/WHEEL
visualone-0.0.20.dist-info/top_level.txt
visualone-0.0.20.dist-info/RECORD
