Metadata-Version: 2.1
Name: visualone
Version: 0.0.20
Summary: Python API for Visual One's few shot learning framework.
Home-page: https://visualone.tech
Author: Visual One Technologies Inc.
Author-email: contact@visualone.tech
License: UNKNOWN
Platform: UNKNOWN
Classifier: Programming Language :: Python :: 3
Classifier: License :: OSI Approved :: MIT License
Classifier: Operating System :: OS Independent
Requires-Python: >=3.6
